neuralake/__init__.py
neuralake/roapi_export.py
neuralake/web_export.py
neuralake/core/__init__.py
neuralake/core/catalog/__init__.py
neuralake/core/catalog/catalog.py
neuralake/core/dataframe/__init__.py
neuralake/core/dataframe/frame.py
neuralake/core/tables/__init__.py
neuralake/core/tables/decorator.py
neuralake/core/tables/deltalake_table.py
neuralake/core/tables/filters.py
neuralake/core/tables/metadata.py
neuralake/core/tables/parquet_table.py
neuralake/core/tables/util.py
neuralake/export/static_site/.gitignore
neuralake/export/static_site/README.md
neuralake/export/static_site/build.py
neuralake/export/static_site/package-lock.json
neuralake/export/static_site/package.json
neuralake/export/static_site/tsconfig.json
neuralake/export/static_site/tsconfig.node.json
neuralake/export/static_site/vite.config.ts
neuralake/export/static_site/precompiled/favicon.png
neuralake/export/static_site/precompiled/index.html
neuralake/export/static_site/precompiled/assets/abap-DsBKuouk.js
neuralake/export/static_site/precompiled/assets/abap-DsBKuouk.js.map
neuralake/export/static_site/precompiled/assets/actionscript-3-D_z4Izcz.js
neuralake/export/static_site/precompiled/assets/actionscript-3-D_z4Izcz.js.map
neuralake/export/static_site/precompiled/assets/ada-727ZlQH0.js
neuralake/export/static_site/precompiled/assets/ada-727ZlQH0.js.map
neuralake/export/static_site/precompiled/assets/andromeeda-C3khCPGq.js
neuralake/export/static_site/precompiled/assets/andromeeda-C3khCPGq.js.map
neuralake/export/static_site/precompiled/assets/angular-html-LfdN0zeE.js
neuralake/export/static_site/precompiled/assets/angular-html-LfdN0zeE.js.map
neuralake/export/static_site/precompiled/assets/angular-ts-CKsD7JZE.js
neuralake/export/static_site/precompiled/assets/angular-ts-CKsD7JZE.js.map
neuralake/export/static_site/precompiled/assets/apache-Dn00JSTd.js
neuralake/export/static_site/precompiled/assets/apache-Dn00JSTd.js.map
neuralake/export/static_site/precompiled/assets/apex-COJ4H7py.js
neuralake-0.0.5.dist-info/METADATA
neuralake-0.0.5.dist-info/WHEEL
neuralake-0.0.5.dist-info/RECORD
