Metadata-Version: 2.4
Name: neuralake
Version: 0.0.5
Summary: A simple platform for complex data
Project-URL: Homepage, https://github.com/neuralinkcorp/neuralake_client
Project-URL: Issues, https://github.com/neuralinkcorp/neuralake_client/issues
Author-email: Gautham Acharya <gautacharya@gmail.com>
License: MIT
Classifier: Development Status :: 4 - Beta
Classifier: License :: OSI Approved :: MIT License
Classifier: Operating System :: OS Independent
Classifier: Programming Language :: Python :: 3
Requires-Python: >=3.8
Requires-Dist: boto3==1.26.20
Requires-Dist: deltalake==0.25.4
Requires-Dist: ipython==8.5.0
Requires-Dist: polars==1.9.0
Requires-Dist: pyarrow==17.0.0
Requires-Dist: typing-extensions==4.13.2
Provides-Extra: dev
Requires-Dist: black>=23.0.0; extra == 'dev'
Requires-Dist: flake8>=6.0.0; extra == 'dev'
Requires-Dist: mkdocs-material>=9.6.14; extra == 'dev'
Requires-Dist: mkdocs>=1.5.0; extra == 'dev'
Requires-Dist: mkdocstrings; extra == 'dev'
Requires-Dist: mkdocstrings-python>=1.7.0; extra == 'dev'
Requires-Dist: mypy>=1.0.0; extra == 'dev'
Requires-Dist: pytest-cov>=4.0.0; extra == 'dev'
Requires-Dist: pytest>=7.0.0; extra == 'dev'
